odoo10_addon_pos_backend_partner-10.0.1.0.3-py3.8-nspkg.pth
odoo/addons/pos_backend_partner/README.rst
odoo/addons/pos_backend_partner/__init__.py
odoo/addons/pos_backend_partner/__manifest__.py
odoo/addons/pos_backend_partner/i18n/ca.po
odoo/addons/pos_backend_partner/i18n/es.po
odoo/addons/pos_backend_partner/i18n/fr.po
odoo/addons/pos_backend_partner/i18n/pos_backend_partner.pot
odoo/addons/pos_backend_partner/models/__init__.py
odoo/addons/pos_backend_partner/models/partner.py
odoo/addons/pos_backend_partner/static/description/icon.png
odoo/addons/pos_backend_partner/static/description/pos_backend_partner_1.png
odoo/addons/pos_backend_partner/static/description/pos_backend_partner_2.png
odoo/addons/pos_backend_partner/static/description/pos_backend_partner_3.png
odoo/addons/pos_backend_partner/static/src/css/pos_backend_partner.css
odoo/addons/pos_backend_partner/static/src/js/back_partner.js
odoo/addons/pos_backend_partner/static/src/js/pos_partner.js
odoo/addons/pos_backend_partner/views/assets.xml
odoo/addons/pos_backend_partner/views/backend_partner.xml
odoo10_addon_pos_backend_partner-10.0.1.0.3.dist-info/METADATA
odoo10_addon_pos_backend_partner-10.0.1.0.3.dist-info/WHEEL
odoo10_addon_pos_backend_partner-10.0.1.0.3.dist-info/namespace_packages.txt
odoo10_addon_pos_backend_partner-10.0.1.0.3.dist-info/top_level.txt
odoo10_addon_pos_backend_partner-10.0.1.0.3.dist-info/RECORD
